rizamonga/__init__.py
rizamonga/aggregate.py
rizamonga/count.py
rizamonga/filter.py
rizamonga/find.py
rizamonga/find_one.py
rizamonga/find_one_and_update.py
rizamonga/insert_one.py
rizamonga/monga.py
rizamonga-0.0.1.dist-info/LICENSE
rizamonga-0.0.1.dist-info/METADATA
rizamonga-0.0.1.dist-info/WHEEL
rizamonga-0.0.1.dist-info/top_level.txt
rizamonga-0.0.1.dist-info/RECORD
