Metadata-Version: 2.1
Name: rizamonga
Version: 0.0.1
Summary: A Pymongo Wrapper
Home-page: https://github.com/rizoadev/rizamonga
Author: Riza Masykur
Author-email: hanirizo@gmail.com
License: UNKNOWN
Project-URL: Bug Tracker, https://github.com/rizoadev/rizamonga/issues
Platform: UNKNOWN
Classifier: Programming Language :: Python :: 3
Classifier: License :: OSI Approved :: MIT License
Classifier: Operating System :: OS Independent
Requires-Python: >=3.6
License-File: LICENSE
